{
  "_tag": "Distribution",
  "id": "https://id.skygest.io/distribution/dist_01KNX70F54GHV6NPNR0P37KZJP",
  "datasetId": "https://id.skygest.io/dataset/ds_01KNX70F540JZT2YG7NJ842X9V",
  "kind": "api-access",
  "title": "IESO LMP Real Time 5 Min Ontario Zonal JSON API",
  "description": "Five-minute, real-time, LMP values for the Ontario-wide zonal price in IESO. This Ontario Zonal Price (OZNP) is a load-weighted LMP across the entire province, that passive loads settle against. \n\nThis price is similar to the old Hourly Ontario Energy Price (HOEP), and was part of a compromise in the design of the Market Renewal Program, which originally planned on using aggregate zonal prices for passive load settlement.",
  "accessURL": "https://api.gridstatus.io/v1/datasets/ieso_lmp_real_time_5_min_ontario_zonal/query?return_format=json",
  "mediaType": "application/json",
  "format": "json",
  "accessRights": "public",
  "accessServiceId": "https://id.skygest.io/data-service/svc_01KNQTFC3SCBVEA560C7K0EHV0",
  "createdAt": "2026-04-11T02:47:48.597Z",
  "updatedAt": "2026-04-12T16:29:41.516Z",
  "aliases": [
    {
      "scheme": "url",
      "value": "https://api.gridstatus.io/v1/datasets/ieso_lmp_real_time_5_min_ontario_zonal/query?return_format=json",
      "relation": "exactMatch"
    }
  ]
}
