{
  "_tag": "Distribution",
  "id": "https://id.skygest.io/distribution/dist_01KNX70F5KS2ZZD1V7HMR721K2",
  "datasetId": "https://id.skygest.io/dataset/ds_01KNX70F5JV1NTS2S4T636WCH5",
  "kind": "api-access",
  "title": "PJM Voltage Limits JSON API",
  "description": "This dataset contains daily flow limits across transmission lines that provides PJM default voltage values and voltage stability limits by voltage class. Transmission owners can elect to deviate from PJM, designated by a “no” value in the “follow_pjm” column. Additional, voltage limits, including high, low, and normal kV ratings are included. ",
  "accessURL": "https://api.gridstatus.io/v1/datasets/pjm_voltage_limits/query?return_format=json",
  "mediaType": "application/json",
  "format": "json",
  "accessRights": "public",
  "accessServiceId": "https://id.skygest.io/data-service/svc_01KNQTFC3SCBVEA560C7K0EHV0",
  "createdAt": "2026-04-11T02:47:48.597Z",
  "updatedAt": "2026-04-14T15:26:00.064Z",
  "aliases": [
    {
      "scheme": "url",
      "value": "https://api.gridstatus.io/v1/datasets/pjm_voltage_limits/query?return_format=json",
      "relation": "exactMatch"
    }
  ]
}
