{
  "_tag": "Distribution",
  "id": "https://id.skygest.io/distribution/dist_01KNX70F59SN9TKWDJEMC5M6YP",
  "datasetId": "https://id.skygest.io/dataset/ds_01KNX70F59JYTRVXPQYGWNYZSR",
  "kind": "api-access",
  "title": "ISONE LMP DART Hourly Final JSON API",
  "description": "DART spread in ISONE between day-ahead hourly LMPs and real-time hourly final LMPs. Both day-ahead and real-time values are at hourly intervals.",
  "accessURL": "https://api.gridstatus.io/v1/datasets/isone_lmp_dart_hourly_final/query?return_format=json",
  "mediaType": "application/json",
  "format": "json",
  "accessRights": "public",
  "accessServiceId": "https://id.skygest.io/data-service/svc_01KNQTFC3SCBVEA560C7K0EHV0",
  "createdAt": "2026-04-11T02:47:48.597Z",
  "updatedAt": "2026-04-14T15:26:00.064Z",
  "aliases": [
    {
      "scheme": "url",
      "value": "https://api.gridstatus.io/v1/datasets/isone_lmp_dart_hourly_final/query?return_format=json",
      "relation": "exactMatch"
    }
  ]
}
