{
  "_tag": "Dataset",
  "id": "https://id.skygest.io/dataset/ds_01KNQSXEPT4PS668K7WZ4QAY80",
  "title": "EIA Total Energy",
  "publisherAgentId": "https://id.skygest.io/agent/ag_01KNQEZ5V57VJJJFYV6HWM03VB",
  "aliases": [
    {
      "scheme": "eia-route",
      "value": "TOTAL",
      "relation": "exactMatch"
    }
  ],
  "createdAt": "2026-04-08T00:00:00.000Z",
  "updatedAt": "2026-04-08T00:00:00.000Z",
  "distributionIds": [
    "https://id.skygest.io/distribution/dist_01KNQSXEPTNG93YWW21EQYZZTR",
    "https://id.skygest.io/distribution/dist_01KNQSXEPT369NFW80TQPRAHP0"
  ],
  "description": "U.S. total energy production, prices, carbon dioxide emissions, and consumption by sector and source.",
  "landingPage": "https://www.eia.gov/totalenergy/",
  "keywords": [
    "total energy",
    "production",
    "consumption",
    "prices",
    "emissions"
  ],
  "themes": [
    "total energy"
  ],
  "dataServiceIds": [
    "https://id.skygest.io/data-service/svc_01KNQEZ5VHS74DM94ABW2ZM93Y"
  ],
  "accessRights": "public"
}
