{
  "_tag": "Dataset",
  "id": "https://id.skygest.io/dataset/ds_01KP1ASA1C8A9Z86EF7WBNJKA9",
  "title": "Accepted Offers (Balancing)",
  "description": "Accepted offers for manual and automatic frequency restoration reserves.",
  "publisherAgentId": "https://id.skygest.io/agent/ag_01KNQEZ5VFHVJNF9VV9J3JQGV9",
  "landingPage": "https://transparency.entsoe.eu/",
  "accessRights": "public",
  "keywords": [
    "balancing",
    "Art. 17.1(b)"
  ],
  "themes": [
    "balancing"
  ],
  "distributionIds": [
    "https://id.skygest.io/distribution/dist_01KP1ASA1CKGEWJG1HB084MX4V"
  ],
  "dataServiceIds": [
    "https://id.skygest.io/data-service/svc_01KP1ASA196ZW4HCGRC7TGWS41"
  ],
  "createdAt": "2026-04-12T17:10:46.402Z",
  "updatedAt": "2026-04-12T17:10:46.402Z",
  "aliases": [
    {
      "scheme": "entsoe-document-type",
      "value": "A82",
      "relation": "exactMatch"
    }
  ]
}
