{
  "_tag": "Dataset",
  "id": "https://id.skygest.io/dataset/ds_01KP4W1E26RSEQHT7A8YMVEDH1",
  "title": "Carbon Intensity of Balancing Actions",
  "description": "The carbon intensity of balancing actions measures the difference between the carbon intensity of the combined Final Physical Notice (FPN) of machines in the Balancing Mechanism (BM) and the equivalent profile with balancing actions applied.",
  "publisherAgentId": "https://id.skygest.io/agent/ag_01KP172ZRBS4Z4NGY24XA7YX6D",
  "landingPage": "https://www.neso.energy/data-portal/carbon-intensity-of-balancing-actions",
  "license": "https://www.neso.energy/data-portal/ngeso-open-licence",
  "keywords": [
    "Actions",
    "Balancing",
    "Carbon",
    "Intensity",
    "Subscribable",
    "Carbon intensity",
    "Daily"
  ],
  "themes": [
    "electricity"
  ],
  "distributionIds": [
    "https://id.skygest.io/distribution/dist_01KP4W1E2BSGWX22CX8ZKWFG51",
    "https://id.skygest.io/distribution/dist_01KP4W1E2BBV0V2XKQB22VGW9A"
  ],
  "accessRights": "public",
  "dataServiceIds": [
    "https://id.skygest.io/data-service/svc_01KP4W1DWZG3S96C6XZD3YG71N"
  ],
  "createdAt": "2026-04-14T02:09:59.759Z",
  "updatedAt": "2026-04-14T15:25:34.063Z",
  "aliases": [
    {
      "scheme": "url",
      "value": "https://www.neso.energy/data-portal/carbon-intensity-of-balancing-actions",
      "relation": "exactMatch"
    }
  ]
}
