{
  "_tag": "Dataset",
  "id": "https://id.skygest.io/dataset/ds_01KNQEZ5VRD11P07ZM32C5JRDZ",
  "title": "NREL Geothermal Studies",
  "publisherAgentId": "https://id.skygest.io/agent/ag_01KNQEZ5VF3G335NSS1773RWDH",
  "aliases": [],
  "createdAt": "2026-04-08T00:00:00.000Z",
  "updatedAt": "2026-04-08T00:00:00.000Z",
  "description": "Research on geothermal energy potential and technology",
  "landingPage": "https://www.nrel.gov/geothermal/",
  "keywords": [
    "geothermal",
    "enhanced",
    "superhot"
  ],
  "themes": [
    "geothermal"
  ],
  "distributionIds": [
    "https://id.skygest.io/distribution/dist_01KNQEZ5VR4JGB55590PTJ67GG"
  ],
  "accessRights": "public"
}
