{
  "_tag": "Candidate",
  "id": "https://id.skygest.io/candidate/cand_01KP18ZQ9VZPXHD1KKHEZ28H99",
  "sourceRef": {
    "contentId": "at://did:plc:xc52wj7pj5dmo7ot5tf7gldn/app.bsky.feed.post/3kcyqqv77x42d"
  },
  "resolutionState": "partially_resolved",
  "createdAt": "2026-04-08T00:00:00.000Z",
  "referencedAgentId": "https://id.skygest.io/agent/ag_01KNQEZ5VF8QYJ4ZRG4NNERPQG",
  "referencedDatasetId": "https://id.skygest.io/dataset/ds_01KNQEZ5VQXVN89QWNEDFKX134",
  "referencedDistributionId": "https://id.skygest.io/distribution/dist_01KNQEZ5VQC6CKPFX43G49A89P",
  "referencedVariableId": "https://id.skygest.io/variable/var_01KNQEZ5WNMWFT32DHZE32VG71",
  "referencedSeriesId": "https://id.skygest.io/series/ser_01KNQEZ5XBR1C9VXN2327ZS9P7",
  "rawLabel": "The electrical grid needs a five-fold increase in regional transmission, so the ",
  "rawDims": {
    "geography": "us-ca",
    "category": "price"
  }
}
