{
  "_tag": "CatalogRecord",
  "id": "https://id.skygest.io/catalog-record/cr_01KNX70F50MBVQ6NXYJ8BQSDE1",
  "catalogId": "https://id.skygest.io/catalog/cat_01KNQSXA3M9T29PKZ6966GASNW",
  "primaryTopicType": "dataset",
  "primaryTopicId": "https://id.skygest.io/dataset/ds_01KNX70F508DWGD9F7W63DTPAA",
  "sourceRecordId": "ercot_sced_smne_60_day",
  "harvestedFrom": "https://api.gridstatus.io/v1/datasets",
  "firstSeen": "2023-07-14T21:33:01+00:00",
  "lastSeen": "2026-04-12T11:39:00+00:00",
  "sourceModified": "2026-02-12T05:59:59+00:00",
  "isAuthoritative": true
}
